bio_mimo
