Metadata-Version: 1.1
Name: bio-mimo
Version: 1.1.3
Summary: A MiMo library for biological data
Home-page: https://github.com/childsish/bio-mimo
Author: Liam H. Childs
Author-email: liam.h.childs@gmail.com
License: LICENSE
Platform: UNKNOWN
Classifier: Development Status :: 5 - Production/Stable
Classifier: Intended Audience :: Science/Research
Classifier: Topic :: Scientific/Engineering :: Bio-Informatics
